tgzr/cli/__init__.py
tgzr/cli/__main__.py
tgzr/cli/_version.py
tgzr/cli/add_plugins.py
tgzr/cli/install.py
tgzr/cli/install_cli.py
tgzr/cli/main.py
tgzr/cli/main_cli.py
tgzr/cli/utils.py
tgzr_cli-0.101.dist-info/METADATA
tgzr_cli-0.101.dist-info/WHEEL
tgzr_cli-0.101.dist-info/entry_points.txt
tgzr_cli-0.101.dist-info/licenses/LICENSE
tgzr_cli-0.101.dist-info/RECORD
