Metadata-Version: 2.4
Name: tgzr.cli
Version: 0.101
Summary: tgzr command line interface
Project-URL: Documentation, https://github.com/open-tgzr/tgzr.cli#readme
Project-URL: Issues, https://github.com/open-tgzr/tgzr.cli/issues
Project-URL: Source, https://github.com/open-tgzr/tgzr.cli
Author-email: Dee <dee.sometech@gmail.com>
License-Expression: GPL-3.0-or-later
License-File: LICENSE
Classifier: Development Status :: 4 - Beta
Classifier: Programming Language :: Python
Classifier: Programming Language :: Python :: 3.8
Classifier: Programming Language :: Python :: 3.9
Classifier: Programming Language :: Python :: 3.10
Classifier: Programming Language :: Python :: 3.11
Classifier: Programming Language :: Python :: 3.12
Classifier: Programming Language :: Python :: Implementation :: CPython
Classifier: Programming Language :: Python :: Implementation :: PyPy
Requires-Python: >=3.9
Requires-Dist: click
Requires-Dist: rich>=14.2.0
Requires-Dist: uv>=0.9.15
Provides-Extra: dev
Requires-Dist: pyinstaller>=6.17.0; extra == 'dev'
